Workbook

Sheet nse_sitemap_urls
A1: url | B1: parent | C1: child | D1: depth
A2: https://www.nseindia.com/ | D2: 0
A3: https://www.nseindia.com/invest/file-a-complaint-online | B3: invest | C3: file-a-complaint-online | D3: 2
A4: https://www.nseindia.com/invest/investors-awareness-programs | B4: invest | C4: investors-awareness-programs | D4: 2
A5: https://www.nseindia.com/products-services | C5: products-services | D5: 1
A6: https://www.nseindia.com/regulations/public-notice-compulsory-delisting | B6: regulations | C6: public-notice-compulsory-delisting | D6: 2
A7: https://www.nseindia.com/nse-copyright | C7: nse-copyright | D7: 1
A8: https://www.nseindia.com/market-data/securities-available-for-trading | B8: market-data | C8: securities-available-for-trading | D8: 2
A9: https://www.nseindia.com/invest/first-time-investor-products | B9: invest | C9: first-time-investor-products | D9: 2
A10: https://www.nseindia.com/regulations/listing-compliance | B10: regulations | C10: listing-compliance | D10: 2
A11: https://www.nseindia.com/market-data/stocks-in-call-auction | B11: market-data | C11: stocks-in-call-auction | D11: 2
A12: https://www.nseindia.com/website-policies | C12: website-policies | D12: 1
A13: https://www.nseindia.com/national-stock-exchange/about-nse-company | B13: national-stock-exchange | C13: about-nse-company | D13: 2
A14: https://www.nseindia.com/regulations/public-notice | B14: regulations | C14: public-notice | D14: 2
A15: https://www.nseindia.com/regulations/member-circulars-for-members | B15: regulations | C15: member-circulars-for-members | D15: 2
A16: https://www.nseindia.com/products-services/mf-about-mfss | B16: products-services | C16: mf-about-mfss | D16: 2
A17: https://www.nseindia.com/resources/exchange-communication-holidays | B17: resources | C17: exchange-communication-holidays | D17: 2
A18: https://www.nseindia.com/market-data/eod-historical-data-subscription | B18: market-data | C18: eod-historical-data-subscription | D18: 2
A19: https://www.nseindia.com/feedback/new | B19: feedback | C19: new | D19: 2
A20: https://www.nseindia.com/companies-listing/raising-capital-onboarding-process | B20: companies-listing | C20: raising-capital-onboarding-process | D20: 2
A21: https://www.nseindia.com/companies-listing/compliance-information-compliance-calendar-main-board | B21: companies-listing | C21: compliance-information-compliance-calendar-main-board | D21: 2
A22: https://www.nseindia.com/invest/find-a-stock-broker | B22: invest | C22: find-a-stock-broker | D22: 2
A23: https://www.nseindia.com/national-stock-exchange/nse-volume-business-growth | B23: national-stock-exchange | C23: nse-volume-business-growth | D23: 2
A24: https://www.nseindia.com/trade/members-compliance | B24: trade | C24: members-compliance | D24: 2
... A38: https://www.nseindia.com/trade/deposits-networth-requirements-for-membership | B38: trade | C38: deposits-networth-requirements-for-membership | D38: 2
A39: https://www.nseindia.com/nse-indices | C39: nse-indices | D39: 1
A40: https://www.nseindia.com/products-services/about-equity-derivatives | B40: products-services | C40: about-equity-derivatives | D40: 2
A41: https://www.nseindia.com/learn/academic-calendar | B41: learn | C41: academic-calendar | D41: 2
A42: https://www.nseindia.com/learn/process-to-register-ncfm-nse-certification-in-financial-markets | B42: learn | C42: process-to-register-ncfm-nse-certification-in-financial-markets | D42: 2
A43: https://www.nseindia.com/invest/about-arbitration | B43: invest | C43: about-arbitration | D43: 2
A44: https://www.nseindia.com/companies-listing/corporate-filings-financial-results | B44: companies-listing | C44: corporate-filings-financial-results | D44: 2
A45: https://www.nseindia.com/all-reports | C45: all-reports | D45: 1
A46: https://www.nseindia.com/companies-listing/corporate-filings-directory | B46: companies-listing | C46: corporate-filings-directory | D46: 2
A47: https://www.nseindia.com/trade/membership-suspension-expulsion | B47: trade | C47: membership-suspension-expulsion | D47: 2
A48: https://www.nseindia.com/companies-listing/corporate-filings-announcements | B48: companies-listing | C48: corporate-filings-announcements | D48: 2
A49: https://www.nseindia.com/trade/platform-services-connectivity | B49: trade | C49: platform-services-connectivity | D49: 2
A50: https://www.nseindia.com/market-data/data-subscription-fees | B50: market-data | C50: data-subscription-fees | D50: 2
A51: https://www.nseindia.com/learn/post-graduate-program-full-time | B51: learn | C51: post-graduate-program-full-time | D51: 2
A52: https://www.nseindia.com/all-reports-derivatives | C52: all-reports-derivatives | D52: 1
A53: https://www.nseindia.com/products-services/about-indices | B53: products-services | C53: about-indices | D53: 2
A54: https://www.nseindia.com/market-data/most-active-contracts | B54: market-data | C54: most-active-contracts | D54: 2
A55: https://www.nseindia.com/nse-international-exchange/about | B55: nse-international-exchange | C55: about | D55: 2
A56: https://www.nseindia.com/learn/recorded-courses | B56: learn | C56: recorded-courses | D56: 2
A57: https://www.nseindia.com/market-data/analysis-and-tools-capital-market-snapshot | B57: market-data | C57: analysis-and-tools-capital-market-snapshot | D57: 2
A58: https://www.nseindia.com/regulations/member-sebi-debarred-entities | B58: regulations | C58: member-sebi-debarred-entities | D58: 2
A59: https://www.nseindia.com/submit-tipoff | C59: submit-tipoff | D59: 1
A60: https://www.nseindia.com/products-services/about-equity-market | B60: products-services | C60: about-equity-market | D60: 2
A61: https://www.nseindia.com/resources/historical-reports-capital-market-daily-monthly-archives | B61: resources | C61: historical-reports-capital-market-daily-monthly-archives | D61: 2
A62: https://www.nseindia.com/event-gallery | C62: event-gallery | D62: 1
A63: https://www.nseindia.com/market-data/legend-of-series | B63: market-data | C63: legend-of-series | D63: 2
A64: https://www.nseindia.com/companies-listing/raising-capital-further-issues-main-sme-checklist | B64: companies-listing | C64: raising-capital-further-issues-main-sme-checklist | D64: 2
A65: https://www.nseindia.com/sitemap | C65: sitemap | D65: 1
A66: https://www.nseindia.com/invest/first-time-investor-getting-started | B66: invest | C66: first-time-investor-getting-started | D66: 2
A67: https://www.nseindia.com/market-data/live-equity-market?symbol=NIFTY%2050 | B67: market-data | C67: live-equity-market | D67: 2
A68: https://www.nseindia.com/resources/forms-formats-members | B68: resources | C68: forms-formats-members | D68: 2
A69: https://www.nseindia.com/nse-disclaimer | C69: nse-disclaimer | D69: 1
A70: https://www.nseindia.com/regulations/exchange-market-regulations-rules-byelaws-nseil | B70: regulations | C70: exchange-market-regulations-rules-byelaws-nseil | D70: 2
A71: https://www.nseindia.com/trade/members-homepage | B71: trade | C71: members-homepage | D71: 2
A72: https://www.nseindia.com/investor-relations/announcements | B72: investor-relations | C72: announcements | D72: 2
A73: https://www.nseindia.com/products-services/currency-derivatives-contact-specification-cross-currency | B73: products-services | C73: currency-derivatives-contact-specification-cross-currency | D73: 2
A74: https://www.nseindia.com/learn/overview-about-nse-academy | B74: learn | C74: overview-about-nse-academy | D74: 2
A75: https://www.nseindia.com/invest/investors-regulatory-actions | B75: invest | C75: investors-regulatory-actions | D75: 2
A76: https://www.nseindia.com/all-reports/historical-equities-fii-fpi-dii-trading-activity | B76: all-reports | C76: historical-equities-fii-fpi-dii-trading-activity | D76: 2
A77: https://www.nseindia.com/market-data/securities-lending-and-borrowing | B77: market-data | C77: securities-lending-and-borrowing | D77: 2
A78: https://www.nseindia.com/companies-listing/xbrl-information | B78: companies-listing | C78: xbrl-information | D78: 2
A79: https://www.nseindia.com/nse-academy/nse-academy-overview | B79: nse-academy | C79: nse-academy-overview | D79: 2
A80: https://www.nseindia.com/trade/platform-services-test-market-facility | B80: trade | C80: platform-services-test-market-facility | D80: 2
A81: https://www.nseindia.com/products-services/emerge-platform-about-sme | B81: products-services | C81: emerge-platform-about-sme | D81: 2
... A83: https://www.nseindia.com/market-data/commodity-derivatives | B83: market-data | C83: commodity-derivatives | D83: 2
A84: https://www.nseindia.com/nse-terms-of-use | C84: nse-terms-of-use | D84: 1
A85: https://www.nseindia.com/regulations/list-complaint-status-against-companies-report | B85: regulations | C85: list-complaint-status-against-companies-report | D85: 2
A86: https://www.nseindia.com/regulations/unsolicited-messages-report | B86: regulations | C86: unsolicited-messages-report | D86: 2
A87: https://www.nseindia.com/resources/exchange-communication-circulars | B87: resources | C87: exchange-communication-circulars | D87: 2
A88: https://www.nseindia.com/market-data/equity-derivatives-watch | B88: market-data | C88: equity-derivatives-watch | D88: 2
A89: https://www.nseindia.com/ChartApp/install/charts/mainpage.jsp | B89: charts | C89: mainpage.jsp | D89: 4
A90: https://www.nseindia.com/resources/exchange-communication-press-releases | B90: resources | C90: exchange-communication-press-releases | D90: 2
A91: https://www.nseindia.com/learn/nse-knowledge-hub | B91: learn | C91: nse-knowledge-hub | D91: 2
A92: https://www.nseindia.com/nseint_clearing/nse-international-clearing-overview | B92: nseint_clearing | C92: nse-international-clearing-overview | D92: 2
A93: https://www.nseindia.com/products-services/about-currency-derivatives | B93: products-services | C93: about-currency-derivatives | D93: 2
A94: https://www.nseindia.com/market-data/live-market-indices | B94: market-data | C94: live-market-indices | D94: 2
A95: https://www.nseindia.com/invest/process-of-making-a-complaint | B95: invest | C95: process-of-making-a-complaint | D95: 2
A96: https://www.nseindia.com/regulations/exchange-disclosures-nsccl-iosco-core-sgf-default-waterfall | B96: regulations | C96: exchange-disclosures-nsccl-iosco-core-sgf-default-waterfall | D96: 2
... A101: https://www.nseindia.com/learn/self-study-ncfm-modules-all | B101: learn | C101: self-study-ncfm-modules-all | D101: 2
A102: https://www.nseindia.com/nsetech | C102: nsetech | D102: 1
A103: https://www.nseindia.com/resources/insights-panel-discussions-seminars-corporate-governance | B103: resources | C103: insights-panel-discussions-seminars-corporate-governance | D103: 2
A104: https://www.nseindia.com/market-data/all-upcoming-issues-ipo | B104: market-data | C104: all-upcoming-issues-ipo | D104: 2
A105: https://www.nseindia.com/market-data/live-equity-market | B105: market-data | C105: live-equity-market | D105: 2
A106: https://www.nseindia.com/companies-listing/corporate-filings-actions | B106: companies-listing | C106: corporate-filings-actions | D106: 2
A107: https://www.nseindia.com/market-timings-holidays/contingency-drill-calendar | B107: market-timings-holidays | C107: contingency-drill-calendar | D107: 2
A108: https://www.nseindia.com/learn/courses-for-under-graduates | B108: learn | C108: courses-for-under-graduates | D108: 2
A109: https://www.nseindia.com/companies-listing/listing-processing-fees-for-equity-segment | B109: companies-listing | C109: listing-processing-fees-for-equity-segment | D109: 2
A110: https://www.nseindia.com/companies-listing/corporate-filings-board-meetings | B110: companies-listing | C110: corporate-filings-board-meetings | D110: 2
A111: https://www.nseindia.com/resources/insights-working-paper-series | B111: resources | C111: insights-working-paper-series | D111: 2
A112: https://www.nseindia.com/market-data/liquidity-enhancement-scheme | B112: market-data | C112: liquidity-enhancement-scheme | D112: 2
A113: https://www.nseindia.com/trade/platform-services-non-neat-front-end | B113: trade | C113: platform-services-non-neat-front-end | D113: 2
A114: https://www.nseindia.com/trade/members-change-in-name | B114: trade | C114: members-change-in-name | D114: 2
... A119: https://www.nseindia.com/market-data/new-stock-exchange-listings-today | B119: market-data | C119: new-stock-exchange-listings-today | D119: 2
A120: https://www.nseindia.com/all-reports-debt | C120: all-reports-debt | D120: 1
A121: https://www.nseindia.com/nse-investments | C121: nse-investments | D121: 1
A122: https://www.nseindia.com/contact/corporate-office | B122: contact | C122: corporate-office | D122: 2
...

Sheet Sheet1
A1: url | B1: url | E1: 1 | F1: 2 | G1: 3 | H1: 4
A2: https://www.nseindia.com/ | B2: https: | D2: www.nseindia.com
A3: https://www.nseindia.com/invest/file-a-complaint-online | B3: https: | D3: www.nseindia.com | E3: invest | F3: file-a-complaint-online
A4: https://www.nseindia.com/invest/investors-awareness-programs | B4: https: | D4: www.nseindia.com | E4: invest | F4: investors-awareness-programs
A5: https://www.nseindia.com/products-services | B5: https: | D5: www.nseindia.com | E5: products-services
A6: https://www.nseindia.com/regulations/public-notice-compulsory-delisting | B6: https: | D6: www.nseindia.com | E6: regulations | F6: public-notice-compulsory-delisting
A7: https://www.nseindia.com/nse-copyright | B7: https: | D7: www.nseindia.com | E7: nse-copyright
A8: https://www.nseindia.com/market-data/securities-available-for-trading | B8: https: | D8: www.nseindia.com | E8: market-data | F8: securities-available-for-trading
A9: https://www.nseindia.com/invest/first-time-investor-products | B9: https: | D9: www.nseindia.com | E9: invest | F9: first-time-investor-products
A10: https://www.nseindia.com/regulations/listing-compliance | B10: https: | D10: www.nseindia.com | E10: regulations | F10: listing-compliance
A11: https://www.nseindia.com/market-data/stocks-in-call-auction | B11: https: | D11: www.nseindia.com | E11: market-data | F11: stocks-in-call-auction
A12: https://www.nseindia.com/website-policies | B12: https: | D12: www.nseindia.com | E12: website-policies
A13: https://www.nseindia.com/national-stock-exchange/about-nse-company | B13: https: | D13: www.nseindia.com | E13: national-stock-exchange | F13: about-nse-company
A14: https://www.nseindia.com/regulations/public-notice | B14: https: | D14: www.nseindia.com | E14: regulations | F14: public-notice
A15: https://www.nseindia.com/regulations/member-circulars-for-members | B15: https: | D15: www.nseindia.com | E15: regulations | F15: member-circulars-for-members
A16: https://www.nseindia.com/products-services/mf-about-mfss | B16: https: | D16: www.nseindia.com | E16: products-services | F16: mf-about-mfss
A17: https://www.nseindia.com/resources/exchange-communication-holidays | B17: https: | D17: www.nseindia.com | E17: resources | F17: exchange-communication-holidays
A18: https://www.nseindia.com/market-data/eod-historical-data-subscription | B18: https: | D18: www.nseindia.com | E18: market-data | F18: eod-historical-data-subscription
A19: https://www.nseindia.com/feedback/new | B19: https: | D19: www.nseindia.com | E19: feedback | F19: new
A20: https://www.nseindia.com/companies-listing/raising-capital-onboarding-process | B20: https: | D20: www.nseindia.com | E20: companies-listing | F20: raising-capital-onboarding-process
A21: https://www.nseindia.com/companies-listing/compliance-information-compliance-calendar-main-board | B21: https: | D21: www.nseindia.com | E21: companies-listing | F21: compliance-information-compliance-calendar-main-board
A22: https://www.nseindia.com/invest/find-a-stock-broker | B22: https: | D22: www.nseindia.com | E22: invest | F22: find-a-stock-broker
A23: https://www.nseindia.com/national-stock-exchange/nse-volume-business-growth | B23: https: | D23: www.nseindia.com | E23: national-stock-exchange | F23: nse-volume-business-growth
A24: https://www.nseindia.com/trade/members-compliance | B24: https: | D24: www.nseindia.com | E24: trade | F24: members-compliance
... A38: https://www.nseindia.com/trade/deposits-networth-requirements-for-membership | B38: https: | D38: www.nseindia.com | E38: trade | F38: deposits-networth-requirements-for-membership
A39: https://www.nseindia.com/nse-indices | B39: https: | D39: www.nseindia.com | E39: nse-indices
A40: https://www.nseindia.com/products-services/about-equity-derivatives | B40: https: | D40: www.nseindia.com | E40: products-services | F40: about-equity-derivatives
A41: https://www.nseindia.com/learn/academic-calendar | B41: https: | D41: www.nseindia.com | E41: learn | F41: academic-calendar
A42: https://www.nseindia.com/learn/process-to-register-ncfm-nse-certification-in-financial-markets | B42: https: | D42: www.nseindia.com | E42: learn | F42: process-to-register-ncfm-nse-certification-in-financial-markets
A43: https://www.nseindia.com/invest/about-arbitration | B43: https: | D43: www.nseindia.com | E43: invest | F43: about-arbitration
A44: https://www.nseindia.com/companies-listing/corporate-filings-financial-results | B44: https: | D44: www.nseindia.com | E44: companies-listing | F44: corporate-filings-financial-results
A45: https://www.nseindia.com/all-reports | B45: https: | D45: www.nseindia.com | E45: all-reports
A46: https://www.nseindia.com/companies-listing/corporate-filings-directory | B46: https: | D46: www.nseindia.com | E46: companies-listing | F46: corporate-filings-directory
A47: https://www.nseindia.com/trade/membership-suspension-expulsion | B47: https: | D47: www.nseindia.com | E47: trade | F47: membership-suspension-expulsion
A48: https://www.nseindia.com/companies-listing/corporate-filings-announcements | B48: https: | D48: www.nseindia.com | E48: companies-listing | F48: corporate-filings-announcements
A49: https://www.nseindia.com/trade/platform-services-connectivity | B49: https: | D49: www.nseindia.com | E49: trade | F49: platform-services-connectivity
A50: https://www.nseindia.com/market-data/data-subscription-fees | B50: https: | D50: www.nseindia.com | E50: market-data | F50: data-subscription-fees
A51: https://www.nseindia.com/learn/post-graduate-program-full-time | B51: https: | D51: www.nseindia.com | E51: learn | F51: post-graduate-program-full-time
A52: https://www.nseindia.com/all-reports-derivatives | B52: https: | D52: www.nseindia.com | E52: all-reports-derivatives
A53: https://www.nseindia.com/products-services/about-indices | B53: https: | D53: www.nseindia.com | E53: products-services | F53: about-indices
A54: https://www.nseindia.com/market-data/most-active-contracts | B54: https: | D54: www.nseindia.com | E54: market-data | F54: most-active-contracts
A55: https://www.nseindia.com/nse-international-exchange/about | B55: https: | D55: www.nseindia.com | E55: nse-international-exchange | F55: about
A56: https://www.nseindia.com/learn/recorded-courses | B56: https: | D56: www.nseindia.com | E56: learn | F56: recorded-courses
A57: https://www.nseindia.com/market-data/analysis-and-tools-capital-market-snapshot | B57: https: | D57: www.nseindia.com | E57: market-data | F57: analysis-and-tools-capital-market-snapshot
A58: https://www.nseindia.com/regulations/member-sebi-debarred-entities | B58: https: | D58: www.nseindia.com | E58: regulations | F58: member-sebi-debarred-entities
A59: https://www.nseindia.com/submit-tipoff | B59: https: | D59: www.nseindia.com | E59: submit-tipoff
A60: https://www.nseindia.com/products-services/about-equity-market | B60: https: | D60: www.nseindia.com | E60: products-services | F60: about-equity-market
A61: https://www.nseindia.com/resources/historical-reports-capital-market-daily-monthly-archives | B61: https: | D61: www.nseindia.com | E61: resources | F61: historical-reports-capital-market-daily-monthly-archives
A62: https://www.nseindia.com/event-gallery | B62: https: | D62: www.nseindia.com | E62: event-gallery
A63: https://www.nseindia.com/market-data/legend-of-series | B63: https: | D63: www.nseindia.com | E63: market-data | F63: legend-of-series
A64: https://www.nseindia.com/companies-listing/raising-capital-further-issues-main-sme-checklist | B64: https: | D64: www.nseindia.com | E64: companies-listing | F64: raising-capital-further-issues-main-sme-checklist
A65: https://www.nseindia.com/sitemap | B65: https: | D65: www.nseindia.com | E65: sitemap
A66: https://www.nseindia.com/invest/first-time-investor-getting-started | B66: https: | D66: www.nseindia.com | E66: invest | F66: first-time-investor-getting-started
A67: https://www.nseindia.com/market-data/live-equity-market?symbol=NIFTY%2050 | B67: https: | D67: www.nseindia.com | E67: market-data | F67: live-equity-market?symbol=NIFTY%2050
A68: https://www.nseindia.com/resources/forms-formats-members | B68: https: | D68: www.nseindia.com | E68: resources | F68: forms-formats-members
A69: https://www.nseindia.com/nse-disclaimer | B69: https: | D69: www.nseindia.com | E69: nse-disclaimer
A70: https://www.nseindia.com/regulations/exchange-market-regulations-rules-byelaws-nseil | B70: https: | D70: www.nseindia.com | E70: regulations | F70: exchange-market-regulations-rules-byelaws-nseil
A71: https://www.nseindia.com/trade/members-homepage | B71: https: | D71: www.nseindia.com | E71: trade | F71: members-homepage
A72: https://www.nseindia.com/investor-relations/announcements | B72: https: | D72: www.nseindia.com | E72: investor-relations | F72: announcements
A73: https://www.nseindia.com/products-services/currency-derivatives-contact-specification-cross-currency | B73: https: | D73: www.nseindia.com | E73: products-services | F73: currency-derivatives-contact-specification-cross-currency
A74: https://www.nseindia.com/learn/overview-about-nse-academy | B74: https: | D74: www.nseindia.com | E74: learn | F74: overview-about-nse-academy
A75: https://www.nseindia.com/invest/investors-regulatory-actions | B75: https: | D75: www.nseindia.com | E75: invest | F75: investors-regulatory-actions
A76: https://www.nseindia.com/all-reports/historical-equities-fii-fpi-dii-trading-activity | B76: https: | D76: www.nseindia.com | E76: all-reports | F76: historical-equities-fii-fpi-dii-trading-activity
A77: https://www.nseindia.com/market-data/securities-lending-and-borrowing | B77: https: | D77: www.nseindia.com | E77: market-data | F77: securities-lending-and-borrowing
A78: https://www.nseindia.com/companies-listing/xbrl-information | B78: https: | D78: www.nseindia.com | E78: companies-listing | F78: xbrl-information
A79: https://www.nseindia.com/nse-academy/nse-academy-overview | B79: https: | D79: www.nseindia.com | E79: nse-academy | F79: nse-academy-overview
A80: https://www.nseindia.com/trade/platform-services-test-market-facility | B80: https: | D80: www.nseindia.com | E80: trade | F80: platform-services-test-market-facility
A81: https://www.nseindia.com/products-services/emerge-platform-about-sme | B81: https: | D81: www.nseindia.com | E81: products-services | F81: emerge-platform-about-sme
... A83: https://www.nseindia.com/market-data/commodity-derivatives | B83: https: | D83: www.nseindia.com | E83: market-data | F83: commodity-derivatives
A84: https://www.nseindia.com/nse-terms-of-use | B84: https: | D84: www.nseindia.com | E84: nse-terms-of-use
A85: https://www.nseindia.com/regulations/list-complaint-status-against-companies-report | B85: https: | D85: www.nseindia.com | E85: regulations | F85: list-complaint-status-against-companies-report
A86: https://www.nseindia.com/regulations/unsolicited-messages-report | B86: https: | D86: www.nseindia.com | E86: regulations | F86: unsolicited-messages-report
A87: https://www.nseindia.com/resources/exchange-communication-circulars | B87: https: | D87: www.nseindia.com | E87: resources | F87: exchange-communication-circulars
A88: https://www.nseindia.com/market-data/equity-derivatives-watch | B88: https: | D88: www.nseindia.com | E88: market-data | F88: equity-derivatives-watch
A89: https://www.nseindia.com/resources/exchange-communication-press-releases | B89: https: | D89: www.nseindia.com | E89: resources | F89: exchange-communication-press-releases
A90: https://www.nseindia.com/learn/nse-knowledge-hub | B90: https: | D90: www.nseindia.com | E90: learn | F90: nse-knowledge-hub
A91: https://www.nseindia.com/nseint_clearing/nse-international-clearing-overview | B91: https: | D91: www.nseindia.com | E91: nseint_clearing | F91: nse-international-clearing-overview
A92: https://www.nseindia.com/products-services/about-currency-derivatives | B92: https: | D92: www.nseindia.com | E92: products-services | F92: about-currency-derivatives
A93: https://www.nseindia.com/market-data/live-market-indices | B93: https: | D93: www.nseindia.com | E93: market-data | F93: live-market-indices
A94: https://www.nseindia.com/invest/process-of-making-a-complaint | B94: https: | D94: www.nseindia.com | E94: invest | F94: process-of-making-a-complaint
A95: https://www.nseindia.com/regulations/exchange-disclosures-nsccl-iosco-core-sgf-default-waterfall | B95: https: | D95: www.nseindia.com | E95: regulations | F95: exchange-disclosures-nsccl-iosco-core-sgf-default-waterfall
A96: https://www.nseindia.com/companies-listing/corporate-filings-event-calendar?days=today | B96: https: | D96: www.nseindia.com | E96: companies-listing | F96: corporate-filings-event-calendar?days=today
... A100: https://www.nseindia.com/learn/self-study-ncfm-modules-all | B100: https: | D100: www.nseindia.com | E100: learn | F100: self-study-ncfm-modules-all
A101: https://www.nseindia.com/nsetech | B101: https: | D101: www.nseindia.com | E101: nsetech
A102: https://www.nseindia.com/resources/insights-panel-discussions-seminars-corporate-governance | B102: https: | D102: www.nseindia.com | E102: resources | F102: insights-panel-discussions-seminars-corporate-governance
A103: https://www.nseindia.com/market-data/all-upcoming-issues-ipo | B103: https: | D103: www.nseindia.com | E103: market-data | F103: all-upcoming-issues-ipo
A104: https://www.nseindia.com/market-data/live-equity-market | B104: https: | D104: www.nseindia.com | E104: market-data | F104: live-equity-market
A105: https://www.nseindia.com/companies-listing/corporate-filings-actions | B105: https: | D105: www.nseindia.com | E105: companies-listing | F105: corporate-filings-actions
A106: https://www.nseindia.com/market-timings-holidays/contingency-drill-calendar | B106: https: | D106: www.nseindia.com | E106: market-timings-holidays | F106: contingency-drill-calendar
A107: https://www.nseindia.com/learn/courses-for-under-graduates | B107: https: | D107: www.nseindia.com | E107: learn | F107: courses-for-under-graduates
A108: https://www.nseindia.com/companies-listing/listing-processing-fees-for-equity-segment | B108: https: | D108: www.nseindia.com | E108: companies-listing | F108: listing-processing-fees-for-equity-segment
A109: https://www.nseindia.com/companies-listing/corporate-filings-board-meetings | B109: https: | D109: www.nseindia.com | E109: companies-listing | F109: corporate-filings-board-meetings
A110: https://www.nseindia.com/resources/insights-working-paper-series | B110: https: | D110: www.nseindia.com | E110: resources | F110: insights-working-paper-series
A111: https://www.nseindia.com/market-data/liquidity-enhancement-scheme | B111: https: | D111: www.nseindia.com | E111: market-data | F111: liquidity-enhancement-scheme
A112: https://www.nseindia.com/trade/platform-services-non-neat-front-end | B112: https: | D112: www.nseindia.com | E112: trade | F112: platform-services-non-neat-front-end
A113: https://www.nseindia.com/trade/members-change-in-name | B113: https: | D113: www.nseindia.com | E113: trade | F113: members-change-in-name
... A118: https://www.nseindia.com/market-data/new-stock-exchange-listings-today | B118: https: | D118: www.nseindia.com | E118: market-data | F118: new-stock-exchange-listings-today
A119: https://www.nseindia.com/all-reports-debt | B119: https: | D119: www.nseindia.com | E119: all-reports-debt
A120: https://www.nseindia.com/nse-investments | B120: https: | D120: www.nseindia.com | E120: nse-investments
A121: https://www.nseindia.com/contact/corporate-office | B121: https: | D121: www.nseindia.com | E121: contact | F121: corporate-office
...

Sheet Sheet2
E1: part 1 | F1: count
E2: products-services | F2: =COUNTIF(Sheet1!$E$2:$E$1175,E2) -> 329
E3: get-quotes | F3: =COUNTIF(Sheet1!$E$2:$E$1175,E3) -> 230
E4: learn | F4: =COUNTIF(Sheet1!$E$2:$E$1175,E4) -> 111
E5: trade | F5: =COUNTIF(Sheet1!$E$2:$E$1175,E5) -> 75
E6: companies-listing | F6: =COUNTIF(Sheet1!$E$2:$E$1175,E6) -> 70
E7: market-data | F7: =COUNTIF(Sheet1!$E$2:$E$1175,E7) -> 52
E8: invest | F8: =COUNTIF(Sheet1!$E$2:$E$1175,E8) -> 50
E9: resources | F9: =COUNTIF(Sheet1!$E$2:$E$1175,E9) -> 32
E10: regulations | F10: =COUNTIF(Sheet1!$E$2:$E$1175,E10) -> 31
E11: nse-clearing | F11: =COUNTIF(Sheet1!$E$2:$E$1175,E11) -> 29
E12: nse-foundation | F12: =COUNTIF(Sheet1!$E$2:$E$1175,E12) -> 14
E13: nse-international-exchange | F13: =COUNTIF(Sheet1!$E$2:$E$1175,E13) -> 13
... E77: market-timings-holidays | F77: =COUNTIF(Sheet1!$E$2:$E$1175,E77) -> 1

Sheet Sheet4

Sheet products-services
E1: child1 | F1: child2 | G1: child3
C2: products-services | D2: about-commodity-derivatives
D3: about-corporate-bonds
D4: about-currency-derivatives
D5: about-electronic-bidding-platform | E5: documents-for-ncd-issues | F5: circulars | G5: operating-guidelines
D6: about-equity-derivatives
D7: about-equity-market
D8: about-etfs
D9: about-indices
D10: about-initial-public-offerings
D11: about-innovators-growth-platform
D12: about-institutional-placement-program
D13: about-interest-rate-derivatives
D14: about-negotiated-trade-reporting-platform
D15: about-nmf-getting-on-to
D16: about-nmf-platform
D17: about-nmf-platform-key-benefits
... D326: tri-party-repo-timings-holidays
